oink/__init__.py
oink/accounts.py
oink/budget.py
oink/category.py
oink/cli.py
oink/colorize.py
oink/db.py
oink/router.py
oink/transactions.py
oink/utils.py
oink/reporting/__init__.py
oink/reporting/_html.py
oink/reporting/_json.py
oink/reporting/_txt.py
oink/reporting/reports.py
oink_cli-0.3.2.dist-info/METADATA
oink_cli-0.3.2.dist-info/RECORD
oink_cli-0.3.2.dist-info/WHEEL
oink_cli-0.3.2.dist-info/entry_points.txt
oink_cli-0.3.2.dist-info/top_level.txt
