Metadata-Version: 2.1
Name: oink-cli
Version: 0.3.2
Summary: A CLI budgeting tools for nerds.
Home-page: http://github.com/zach-king/oink
Author: Zachary King
Author-email: kingzach77@gmail.com
License: MIT
Download-URL: https://github.com/zcking/oink/archive/0.3.2.tar.gz
Platform: UNKNOWN
Classifier: License :: OSI Approved :: MIT License
Requires-Python: >=3.6
Requires-Dist: click (==6.4)
Requires-Dist: tabulate (==0.8.2)
